Workbook

Sheet Raw_Data
A1: NBFC Financial Performance Analysis — Raw Data
A2: All figures in Rs. Crore unless noted. Source: Company Annual Reports / Investor Presentations.
A4: Company | B4: FY | C4: Metric | D4: Value (Rs. Cr) | E4: Source / Note
A5: Tata Capital | B5: FY25 | C5: Total Assets | D5: 180237.27 | E5: Standalone Balance Sheet, Mar 2025, Tata Capital AR 2024-25
A6: Tata Capital | B6: FY25 | C6: Total Loans / Advances (Gross) | D6: 155623.56 | E6: Standalone Balance Sheet - Loans, Mar 2025
A7: Tata Capital | B7: FY25 | C7: Total Equity | D7: 28098.84 | E7: Standalone Balance Sheet - Total Equity, Mar 2025
A8: Tata Capital | B8: FY25 | C8: Total Borrowings (Debt Securities + Borrowings + Subordinated Liabilities) | D8: 147337.92 | E8: Debt securities 51,807.61 + Borrowings 87,204.94 + Subordinated liabilities 8,325.37
A9: Tata Capital | B9: FY25 | C9: Interest Income | D9: 19203.46 | E9: Standalone P&L, FY25
A10: Tata Capital | B10: FY25 | C10: Finance Costs (Interest Expense) | D10: 10889.48 | E10: Standalone P&L, FY25
A11: Tata Capital | B11: FY25 | C11: Total Income | D11: 21940.08 | E11: Standalone P&L, FY25
A12: Tata Capital | B12: FY25 | C12: Profit After Tax (PAT) | D12: 2594.28 | E12: Standalone P&L, FY25
A13: Tata Capital | B13: FY25 | C13: CRAR (%) | D13: 16.91 | E13: Notes to Accounts - RBI Disclosures, Mar 2025 (value as %, e.g. 16.91)
A14: Tata Capital | B14: FY25 | C14: CRAR - Tier I (%) | D14: 12.8 | E14: Notes to Accounts - RBI Disclosures, Mar 2025
A15: Tata Capital | B15: FY25 | C15: Gross NPA (Stage 3 Gross Carrying Amount) | D15: 3721.75 | E15: RBI Asset Classification Note, Mar 2025
A16: Tata Capital | B16: FY25 | C16: Total Gross Loans (for GNPA%) | D16: 177953.38 | E16: RBI Asset Classification Note - Total Gross Carrying Amount, Mar 2025
... A69: Manappuram Finance | B69: FY25 | C69: CRAR (%) | D69: 30.91 | E69: Narrative disclosure only (MD's Message / Highlights), standalone, Mar 2025 - no Tier I/II breakdown table available
A70: Manappuram Finance | B70: FY25 | C70: CRAR - Tier I (%) | E70: Not disclosed in a separate table - only overall CRAR % stated narratively
A71: Manappuram Finance | B71: FY25 | C71: Gross NPA (Stage 3 Gross Carrying Amount) | D71: 890.57 | E71: RBI Asset Classification Note, Mar 2025 (converted from Mn)
A72: Manappuram Finance | B72: FY25 | C72: Total Gross Loans (for GNPA%) | D72: 32862.55 | E72: RBI Asset Classification Note - Total Gross Carrying Amount, Mar 2025 (converted from Mn)
A73: Manappuram Finance | B73: FY25 | C73: Net NPA (Stage 3 Net Carrying Amount) | D73: 775.73 | E73: RBI Asset Classification Note, Mar 2025 (converted from Mn)
A74: Manappuram Finance | B74: FY25 | C74: Total Net Loans (for NNPA%) | D74: 32574.9 | E74: RBI Asset Classification Note - Total Net Carrying Amount, Mar 2025 (converted from Mn)
A75: Manappuram Finance | B75: FY24 | C75: Total Assets | D75: 33893.06 | E75: Standalone Balance Sheet, Mar 2024, Manappuram AR 2024-25 comparative (converted from Mn)
A76: Manappuram Finance | B76: FY24 | C76: Total Loans / Advances (Gross) | D76: 29058.89 | E76: Standalone Balance Sheet - Loans, Mar 2024 (converted from Mn)
A77: Manappuram Finance | B77: FY24 | C77: Total Equity | D77: 10349.27 | E77: Standalone Balance Sheet - Total Equity, Mar 2024 (converted from Mn)
A78: Manappuram Finance | B78: FY24 | C78: Total Borrowings (Debt Securities + Borrowings + Subordinated Liabilities) | D78: 22466.83 | E78: Debt securities 4,433.98 + Borrowings 18,032.85 + Subordinated liabilities Nil (converted from Mn)
A79: Manappuram Finance | B79: FY24 | C79: Interest Income | D79: 5754.49 | E79: Standalone P&L, FY24 comparative (converted from Mn)
A80: Manappuram Finance | B80: FY24 | C80: Finance Costs (Interest Expense) | D80: 1828.04 | E80: Standalone P&L, FY24 comparative (converted from Mn)
A81: Manappuram Finance | B81: FY24 | C81: Total Income | D81: 5854.65 | E81: Standalone P&L, FY24 comparative (converted from Mn)
A82: Manappuram Finance | B82: FY24 | C82: Profit After Tax (PAT) | D82: 1657.73 | E82: Standalone P&L, FY24 comparative (converted from Mn)
A83: Manappuram Finance | B83: FY24 | C83: CRAR (%) | E83: Not disclosed in FY24-25 annual report in comparable format for FY24 (only FY25 stated narratively)
A84: Manappuram Finance | B84: FY24 | C84: CRAR - Tier I (%) | E84: Not disclosed
A85: Manappuram Finance | B85: FY24 | C85: Gross NPA (Stage 3 Gross Carrying Amount) | D85: 546.66 | E85: RBI Asset Classification Note, Mar 2024 (converted from Mn)
A86: Manappuram Finance | B86: FY24 | C86: Total Gross Loans (for GNPA%) | D86: 28481.19 | E86: RBI Asset Classification Note - Total Gross Carrying Amount, Mar 2024 (converted from Mn)
A87: Manappuram Finance | B87: FY24 | C87: Net NPA (Stage 3 Net Carrying Amount) | D87: 479.58 | E87: RBI Asset Classification Note, Mar 2024 (converted from Mn)
A88: Manappuram Finance | B88: FY24 | C88: Total Net Loans (for NNPA%) | D88: 28268.88 | E88: RBI Asset Classification Note - Total Net Carrying Amount, Mar 2024 (converted from Mn)

Sheet Ratios
A1: NBFC Financial Ratios — Computed Summary
A2: All ratios calculated from Raw_Data sheet using SUMIFS lookups. Update Raw_Data and these refresh automatically.
A4: Company | B4: FY | C4: NIM (%) | D4: ROA (%) | E4: ROE (%) | F4: Net Profit Margin (%) | G4: Debt-to-Equity (x) | H4: CRAR (%) | I4: GNPA (%) | J4: NNPA (%)
A5: Tata Capital | B5: FY25 | C5: =IFERROR((SUMIFS(Raw_Data!$D$5:$D$88,Raw_Data!$A$5:$A$88,$A5,Raw_Data!$B$5:$B$88,$B5,Raw_Data!$C$5:$C$88,"Interest Income")-SUMIFS(Raw_Data!$D$5:$D$88,Raw_Data!$A$5:$A$88,$A5,Raw_Data!$B$5:$B$88,$B5,Raw_Data!$C$5:$C$88,"Finance Costs (Interest Expense)"))/SUMIFS(Raw_Data!$D$5:$D$88,Raw_Data!$A$5:$A$88,$A5,Raw_Data!$B$5:$B$88,$B5,Raw_Data!$C$5:$C$88,"Total Assets"),"") -> 0.046127973 | D5: =IFERROR(SUMIFS(Raw_Data!$D$5:$D$88,Raw_Data!$A$5:$A$88,$A5,Raw_Data!$B$5:$B$88,$B5,Raw_Data!$C$5:$C$88,"Profit After Tax (PAT)")/SUMIFS(Raw_Data!$D$5:$D$88,Raw_Data!$A$5:$A$88,$A5,Raw_Data!$B$5:$B$88,$B5,Raw_Data!$C$5:$C$88,"Total Assets"),"") -> 0.014393693 | E5: =IFERROR(SUMIFS(Raw_Data!$D$5:$D$88,Raw_Data!$A$5:$A$88,$A5,Raw_Data!$B$5:$B$88,$B5,Raw_Data!$C$5:$C$88,"Profit After Tax (PAT)")/SUMIFS(Raw_Data!$D$5:$D$88,Raw_Data!$A$5:$A$88,$A5,Raw_Data!$B$5:$B$88,$B5,Raw_Data!$C$5:$C$88,"Total Equity"),"") -> 0.092326943 | F5: =IFERROR(SUMIFS(Raw_Data!$D$5:$D$88,Raw_Data!$A$5:$A$88,$A5,Raw_Data!$B$5:$B$88,$B5,Raw_Data!$C$5:$C$88,"Profit After Tax (PAT)")/SUMIFS(Raw_Data!$D$5:$D$88,Raw_Data!$A$5:$A$88,$A5,Raw_Data!$B$5:$B$88,$B5,Raw_Data!$C$5:$C$88,"Total Income"),"") -> 0.11824387 | G5: =IFERROR(SUMIFS(Raw_Data!$D$5:$D$88,Raw_Data!$A$5:$A$88,$A5,Raw_Data!$B$5:$B$88,$B5,Raw_Data!$C$5:$C$88,"Total Borrowings (Debt Securities + Borrowings + Subordinated Liabilities)")/SUMIFS(Raw_Data!$D$5:$D$88,Raw_Data!$A$5:$A$88,$A5,Raw_Data!$B$5:$B$88,$B5,Raw_Data!$C$5:$C$88,"Total Equity"),"") -> 5.2435588 | H5: =IFERROR(SUMIFS(Raw_Data!$D$5:$D$88,Raw_Data!$A$5:$A$88,$A5,Raw_Data!$B$5:$B$88,$B5,Raw_Data!$C$5:$C$88,"CRAR (%)")/100,"") -> 0.1691 | I5: =IFERROR(SUMIFS(Raw_Data!$D$5:$D$88,Raw_Data!$A$5:$A$88,$A5,Raw_Data!$B$5:$B$88,$B5,Raw_Data!$C$5:$C$88,"Gross NPA (Stage 3 Gross Carrying Amount)")/SUMIFS(Raw_Data!$D$5:$D$88,Raw_Data!$A$5:$A$88,$A5,Raw_Data!$B$5:$B$88,$B5,Raw_Data!$C$5:$C$88,"Total Gross Loans (for GNPA%)"),"") -> 0.020914186 | J5: =IFERROR(SUMIFS(Raw_Data!$D$5:$D$88,Raw_Data!$A$5:$A$88,$A5,Raw_Data!$B$5:$B$88,$B5,Raw_Data!$C$5:$C$88,"Net NPA (Stage 3 Net Carrying Amount)")/SUMIFS(Raw_Data!$D$5:$D$88,Raw_Data!$A$5:$A$88,$A5,Raw_Data!$B$5:$B$88,$B5,Raw_Data!$C$5:$C$88,"Total Net Loans (for NNPA%)"),"") -> 0.0088522401
A6: Tata Capital | B6: FY24 | C6: =IFERROR((SUMIFS(Raw_Data!$D$5:$D$88,Raw_Data!$A$5:$A$88,$A6,Raw_Data!$B$5:$B$88,$B6,Raw_Data!$C$5:$C$88,"Interest Income")-SUMIFS(Raw_Data!$D$5:$D$88,Raw_Data!$A$5:$A$88,$A6,Raw_Data!$B$5:$B$88,$B6,Raw_Data!$C$5:$C$88,"Finance Costs (Interest Expense)"))/SUMIFS(Raw_Data!$D$5:$D$88,Raw_Data!$A$5:$A$88,$A6,Raw_Data!$B$5:$B$88,$B6,Raw_Data!$C$5:$C$88,"Total Assets"),"") -> 0.039350882 | D6: =IFERROR(SUMIFS(Raw_Data!$D$5:$D$88,Raw_Data!$A$5:$A$88,$A6,Raw_Data!$B$5:$B$88,$B6,Raw_Data!$C$5:$C$88,"Profit After Tax (PAT)")/SUMIFS(Raw_Data!$D$5:$D$88,Raw_Data!$A$5:$A$88,$A6,Raw_Data!$B$5:$B$88,$B6,Raw_Data!$C$5:$C$88,"Total Assets"),"") -> 0.020147016 | E6: =IFERROR(SUMIFS(Raw_Data!$D$5:$D$88,Raw_Data!$A$5:$A$88,$A6,Raw_Data!$B$5:$B$88,$B6,Raw_Data!$C$5:$C$88,"Profit After Tax (PAT)")/SUMIFS(Raw_Data!$D$5:$D$88,Raw_Data!$A$5:$A$88,$A6,Raw_Data!$B$5:$B$88,$B6,Raw_Data!$C$5:$C$88,"Total Equity"),"") -> 0.12813059 | F6: =IFERROR(SUMIFS(Raw_Data!$D$5:$D$88,Raw_Data!$A$5:$A$88,$A6,Raw_Data!$B$5:$B$88,$B6,Raw_Data!$C$5:$C$88,"Profit After Tax (PAT)")/SUMIFS(Raw_Data!$D$5:$D$88,Raw_Data!$A$5:$A$88,$A6,Raw_Data!$B$5:$B$88,$B6,Raw_Data!$C$5:$C$88,"Total Income"),"") -> 0.18727398 | G6: =IFERROR(SUMIFS(Raw_Data!$D$5:$D$88,Raw_Data!$A$5:$A$88,$A6,Raw_Data!$B$5:$B$88,$B6,Raw_Data!$C$5:$C$88,"Total Borrowings (Debt Securities + Borrowings + Subordinated Liabilities)")/SUMIFS(Raw_Data!$D$5:$D$88,Raw_Data!$A$5:$A$88,$A6,Raw_Data!$B$5:$B$88,$B6,Raw_Data!$C$5:$C$88,"Total Equity"),"") -> 5.1877509 | H6: =IFERROR(SUMIFS(Raw_Data!$D$5:$D$88,Raw_Data!$A$5:$A$88,$A6,Raw_Data!$B$5:$B$88,$B6,Raw_Data!$C$5:$C$88,"CRAR (%)")/100,"") -> 0.1672 | I6: =IFERROR(SUMIFS(Raw_Data!$D$5:$D$88,Raw_Data!$A$5:$A$88,$A6,Raw_Data!$B$5:$B$88,$B6,Raw_Data!$C$5:$C$88,"Gross NPA (Stage 3 Gross Carrying Amount)")/SUMIFS(Raw_Data!$D$5:$D$88,Raw_Data!$A$5:$A$88,$A6,Raw_Data!$B$5:$B$88,$B6,Raw_Data!$C$5:$C$88,"Total Gross Loans (for GNPA%)"),"") -> 0.015138097 | J6: =IFERROR(SUMIFS(Raw_Data!$D$5:$D$88,Raw_Data!$A$5:$A$88,$A6,Raw_Data!$B$5:$B$88,$B6,Raw_Data!$C$5:$C$88,"Net NPA (Stage 3 Net Carrying Amount)")/SUMIFS(Raw_Data!$D$5:$D$88,Raw_Data!$A$5:$A$88,$A6,Raw_Data!$B$5:$B$88,$B6,Raw_Data!$C$5:$C$88,"Total Net Loans (for NNPA%)"),"") -> 0.0033461347
A7: Bajaj Finance | B7: FY25 | C7: =IFERROR((SUMIFS(Raw_Data!$D$5:$D$88,Raw_Data!$A$5:$A$88,$A7,Raw_Data!$B$5:$B$88,$B7,Raw_Data!$C$5:$C$88,"Interest Income")-SUMIFS(Raw_Data!$D$5:$D$88,Raw_Data!$A$5:$A$88,$A7,Raw_Data!$B$5:$B$88,$B7,Raw_Data!$C$5:$C$88,"Finance Costs (Interest Expense)"))/SUMIFS(Raw_Data!$D$5:$D$88,Raw_Data!$A$5:$A$88,$A7,Raw_Data!$B$5:$B$88,$B7,Raw_Data!$C$5:$C$88,"Total Assets"),"") -> 0.090008045 | D7: =IFERROR(SUMIFS(Raw_Data!$D$5:$D$88,Raw_Data!$A$5:$A$88,$A7,Raw_Data!$B$5:$B$88,$B7,Raw_Data!$C$5:$C$88,"Profit After Tax (PAT)")/SUMIFS(Raw_Data!$D$5:$D$88,Raw_Data!$A$5:$A$88,$A7,Raw_Data!$B$5:$B$88,$B7,Raw_Data!$C$5:$C$88,"Total Assets"),"") -> 0.045291869 | E7: =IFERROR(SUMIFS(Raw_Data!$D$5:$D$88,Raw_Data!$A$5:$A$88,$A7,Raw_Data!$B$5:$B$88,$B7,Raw_Data!$C$5:$C$88,"Profit After Tax (PAT)")/SUMIFS(Raw_Data!$D$5:$D$88,Raw_Data!$A$5:$A$88,$A7,Raw_Data!$B$5:$B$88,$B7,Raw_Data!$C$5:$C$88,"Total Equity"),"") -> 0.18934446 | F7: =IFERROR(SUMIFS(Raw_Data!$D$5:$D$88,Raw_Data!$A$5:$A$88,$A7,Raw_Data!$B$5:$B$88,$B7,Raw_Data!$C$5:$C$88,"Profit After Tax (PAT)")/SUMIFS(Raw_Data!$D$5:$D$88,Raw_Data!$A$5:$A$88,$A7,Raw_Data!$B$5:$B$88,$B7,Raw_Data!$C$5:$C$88,"Total Income"),"") -> 0.28040298 | G7: =IFERROR(SUMIFS(Raw_Data!$D$5:$D$88,Raw_Data!$A$5:$A$88,$A7,Raw_Data!$B$5:$B$88,$B7,Raw_Data!$C$5:$C$88,"Total Borrowings (Debt Securities + Borrowings + Subordinated Liabilities)")/SUMIFS(Raw_Data!$D$5:$D$88,Raw_Data!$A$5:$A$88,$A7,Raw_Data!$B$5:$B$88,$B7,Raw_Data!$C$5:$C$88,"Total Equity"),"") -> 3.1276252 | H7: =IFERROR(SUMIFS(Raw_Data!$D$5:$D$88,Raw_Data!$A$5:$A$88,$A7,Raw_Data!$B$5:$B$88,$B7,Raw_Data!$C$5:$C$88,"CRAR (%)")/100,"") -> 0.2193 | I7: =IFERROR(SUMIFS(Raw_Data!$D$5:$D$88,Raw_Data!$A$5:$A$88,$A7,Raw_Data!$B$5:$B$88,$B7,Raw_Data!$C$5:$C$88,"Gross NPA (Stage 3 Gross Carrying Amount)")/SUMIFS(Raw_Data!$D$5:$D$88,Raw_Data!$A$5:$A$88,$A7,Raw_Data!$B$5:$B$88,$B7,Raw_Data!$C$5:$C$88,"Total Gross Loans (for GNPA%)"),"") -> 0.011834638 | J7: =IFERROR(SUMIFS(Raw_Data!$D$5:$D$88,Raw_Data!$A$5:$A$88,$A7,Raw_Data!$B$5:$B$88,$B7,Raw_Data!$C$5:$C$88,"Net NPA (Stage 3 Net Carrying Amount)")/SUMIFS(Raw_Data!$D$5:$D$88,Raw_Data!$A$5:$A$88,$A7,Raw_Data!$B$5:$B$88,$B7,Raw_Data!$C$5:$C$88,"Total Net Loans (for NNPA%)"),"") -> 0.0056525652
A8: Bajaj Finance | B8: FY24 | C8: =IFERROR((SUMIFS(Raw_Data!$D$5:$D$88,Raw_Data!$A$5:$A$88,$A8,Raw_Data!$B$5:$B$88,$B8,Raw_Data!$C$5:$C$88,"Interest Income")-SUMIFS(Raw_Data!$D$5:$D$88,Raw_Data!$A$5:$A$88,$A8,Raw_Data!$B$5:$B$88,$B8,Raw_Data!$C$5:$C$88,"Finance Costs (Interest Expense)"))/SUMIFS(Raw_Data!$D$5:$D$88,Raw_Data!$A$5:$A$88,$A8,Raw_Data!$B$5:$B$88,$B8,Raw_Data!$C$5:$C$88,"Total Assets"),"") -> 0.090822682 | D8: =IFERROR(SUMIFS(Raw_Data!$D$5:$D$88,Raw_Data!$A$5:$A$88,$A8,Raw_Data!$B$5:$B$88,$B8,Raw_Data!$C$5:$C$88,"Profit After Tax (PAT)")/SUMIFS(Raw_Data!$D$5:$D$88,Raw_Data!$A$5:$A$88,$A8,Raw_Data!$B$5:$B$88,$B8,Raw_Data!$C$5:$C$88,"Total Assets"),"") -> 0.042628099 | E8: =IFERROR(SUMIFS(Raw_Data!$D$5:$D$88,Raw_Data!$A$5:$A$88,$A8,Raw_Data!$B$5:$B$88,$B8,Raw_Data!$C$5:$C$88,"Profit After Tax (PAT)")/SUMIFS(Raw_Data!$D$5:$D$88,Raw_Data!$A$5:$A$88,$A8,Raw_Data!$B$5:$B$88,$B8,Raw_Data!$C$5:$C$88,"Total Equity"),"") -> 0.17558696 | F8: =IFERROR(SUMIFS(Raw_Data!$D$5:$D$88,Raw_Data!$A$5:$A$88,$A8,Raw_Data!$B$5:$B$88,$B8,Raw_Data!$C$5:$C$88,"Profit After Tax (PAT)")/SUMIFS(Raw_Data!$D$5:$D$88,Raw_Data!$A$5:$A$88,$A8,Raw_Data!$B$5:$B$88,$B8,Raw_Data!$C$5:$C$88,"Total Income"),"") -> 0.26933318 | G8: =IFERROR(SUMIFS(Raw_Data!$D$5:$D$88,Raw_Data!$A$5:$A$88,$A8,Raw_Data!$B$5:$B$88,$B8,Raw_Data!$C$5:$C$88,"Total Borrowings (Debt Securities + Borrowings + Subordinated Liabilities)")/SUMIFS(Raw_Data!$D$5:$D$88,Raw_Data!$A$5:$A$88,$A8,Raw_Data!$B$5:$B$88,$B8,Raw_Data!$C$5:$C$88,"Total Equity"),"") -> 3.060367 | H8: =IFERROR(SUMIFS(Raw_Data!$D$5:$D$88,Raw_Data!$A$5:$A$88,$A8,Raw_Data!$B$5:$B$88,$B8,Raw_Data!$C$5:$C$88,"CRAR (%)")/100,"") -> 0.2252 | I8: =IFERROR(SUMIFS(Raw_Data!$D$5:$D$88,Raw_Data!$A$5:$A$88,$A8,Raw_Data!$B$5:$B$88,$B8,Raw_Data!$C$5:$C$88,"Gross NPA (Stage 3 Gross Carrying Amount)")/SUMIFS(Raw_Data!$D$5:$D$88,Raw_Data!$A$5:$A$88,$A8,Raw_Data!$B$5:$B$88,$B8,Raw_Data!$C$5:$C$88,"Total Gross Loans (for GNPA%)"),"") -> 0.010491642 | J8: =IFERROR(SUMIFS(Raw_Data!$D$5:$D$88,Raw_Data!$A$5:$A$88,$A8,Raw_Data!$B$5:$B$88,$B8,Raw_Data!$C$5:$C$88,"Net NPA (Stage 3 Net Carrying Amount)")/SUMIFS(Raw_Data!$D$5:$D$88,Raw_Data!$A$5:$A$88,$A8,Raw_Data!$B$5:$B$88,$B8,Raw_Data!$C$5:$C$88,"Total Net Loans (for NNPA%)"),"") -> 0.0046524037
A9: Manappuram Finance | B9: FY25 | C9: =IFERROR((SUMIFS(Raw_Data!$D$5:$D$88,Raw_Data!$A$5:$A$88,$A9,Raw_Data!$B$5:$B$88,$B9,Raw_Data!$C$5:$C$88,"Interest Income")-SUMIFS(Raw_Data!$D$5:$D$88,Raw_Data!$A$5:$A$88,$A9,Raw_Data!$B$5:$B$88,$B9,Raw_Data!$C$5:$C$88,"Finance Costs (Interest Expense)"))/SUMIFS(Raw_Data!$D$5:$D$88,Raw_Data!$A$5:$A$88,$A9,Raw_Data!$B$5:$B$88,$B9,Raw_Data!$C$5:$C$88,"Total Assets"),"") -> 0.11122924 | D9: =IFERROR(SUMIFS(Raw_Data!$D$5:$D$88,Raw_Data!$A$5:$A$88,$A9,Raw_Data!$B$5:$B$88,$B9,Raw_Data!$C$5:$C$88,"Profit After Tax (PAT)")/SUMIFS(Raw_Data!$D$5:$D$88,Raw_Data!$A$5:$A$88,$A9,Raw_Data!$B$5:$B$88,$B9,Raw_Data!$C$5:$C$88,"Total Assets"),"") -> 0.044765771 | E9: =IFERROR(SUMIFS(Raw_Data!$D$5:$D$88,Raw_Data!$A$5:$A$88,$A9,Raw_Data!$B$5:$B$88,$B9,Raw_Data!$C$5:$C$88,"Profit After Tax (PAT)")/SUMIFS(Raw_Data!$D$5:$D$88,Raw_Data!$A$5:$A$88,$A9,Raw_Data!$B$5:$B$88,$B9,Raw_Data!$C$5:$C$88,"Total Equity"),"") -> 0.15121633 | F9: =IFERROR(SUMIFS(Raw_Data!$D$5:$D$88,Raw_Data!$A$5:$A$88,$A9,Raw_Data!$B$5:$B$88,$B9,Raw_Data!$C$5:$C$88,"Profit After Tax (PAT)")/SUMIFS(Raw_Data!$D$5:$D$88,Raw_Data!$A$5:$A$88,$A9,Raw_Data!$B$5:$B$88,$B9,Raw_Data!$C$5:$C$88,"Total Income"),"") -> 0.25790408 | G9: =IFERROR(SUMIFS(Raw_Data!$D$5:$D$88,Raw_Data!$A$5:$A$88,$A9,Raw_Data!$B$5:$B$88,$B9,Raw_Data!$C$5:$C$88,"Total Borrowings (Debt Securities + Borrowings + Subordinated Liabilities)")/SUMIFS(Raw_Data!$D$5:$D$88,Raw_Data!$A$5:$A$88,$A9,Raw_Data!$B$5:$B$88,$B9,Raw_Data!$C$5:$C$88,"Total Equity"),"") -> 2.293417 | H9: =IFERROR(SUMIFS(Raw_Data!$D$5:$D$88,Raw_Data!$A$5:$A$88,$A9,Raw_Data!$B$5:$B$88,$B9,Raw_Data!$C$5:$C$88,"CRAR (%)")/100,"") -> 0.3091 | I9: =IFERROR(SUMIFS(Raw_Data!$D$5:$D$88,Raw_Data!$A$5:$A$88,$A9,Raw_Data!$B$5:$B$88,$B9,Raw_Data!$C$5:$C$88,"Gross NPA (Stage 3 Gross Carrying Amount)")/SUMIFS(Raw_Data!$D$5:$D$88,Raw_Data!$A$5:$A$88,$A9,Raw_Data!$B$5:$B$88,$B9,Raw_Data!$C$5:$C$88,"Total Gross Loans (for GNPA%)"),"") -> 0.027099845 | J9: =IFERROR(SUMIFS(Raw_Data!$D$5:$D$88,Raw_Data!$A$5:$A$88,$A9,Raw_Data!$B$5:$B$88,$B9,Raw_Data!$C$5:$C$88,"Net NPA (Stage 3 Net Carrying Amount)")/SUMIFS(Raw_Data!$D$5:$D$88,Raw_Data!$A$5:$A$88,$A9,Raw_Data!$B$5:$B$88,$B9,Raw_Data!$C$5:$C$88,"Total Net Loans (for NNPA%)"),"") -> 0.023813734
A10: Manappuram Finance | B10: FY24 | C10: =IFERROR((SUMIFS(Raw_Data!$D$5:$D$88,Raw_Data!$A$5:$A$88,$A10,Raw_Data!$B$5:$B$88,$B10,Raw_Data!$C$5:$C$88,"Interest Income")-SUMIFS(Raw_Data!$D$5:$D$88,Raw_Data!$A$5:$A$88,$A10,Raw_Data!$B$5:$B$88,$B10,Raw_Data!$C$5:$C$88,"Finance Costs (Interest Expense)"))/SUMIFS(Raw_Data!$D$5:$D$88,Raw_Data!$A$5:$A$88,$A10,Raw_Data!$B$5:$B$88,$B10,Raw_Data!$C$5:$C$88,"Total Assets"),"") -> 0.1158482 | D10: =IFERROR(SUMIFS(Raw_Data!$D$5:$D$88,Raw_Data!$A$5:$A$88,$A10,Raw_Data!$B$5:$B$88,$B10,Raw_Data!$C$5:$C$88,"Profit After Tax (PAT)")/SUMIFS(Raw_Data!$D$5:$D$88,Raw_Data!$A$5:$A$88,$A10,Raw_Data!$B$5:$B$88,$B10,Raw_Data!$C$5:$C$88,"Total Assets"),"") -> 0.048910603 | E10: =IFERROR(SUMIFS(Raw_Data!$D$5:$D$88,Raw_Data!$A$5:$A$88,$A10,Raw_Data!$B$5:$B$88,$B10,Raw_Data!$C$5:$C$88,"Profit After Tax (PAT)")/SUMIFS(Raw_Data!$D$5:$D$88,Raw_Data!$A$5:$A$88,$A10,Raw_Data!$B$5:$B$88,$B10,Raw_Data!$C$5:$C$88,"Total Equity"),"") -> 0.16017845 | F10: =IFERROR(SUMIFS(Raw_Data!$D$5:$D$88,Raw_Data!$A$5:$A$88,$A10,Raw_Data!$B$5:$B$88,$B10,Raw_Data!$C$5:$C$88,"Profit After Tax (PAT)")/SUMIFS(Raw_Data!$D$5:$D$88,Raw_Data!$A$5:$A$88,$A10,Raw_Data!$B$5:$B$88,$B10,Raw_Data!$C$5:$C$88,"Total Income"),"") -> 0.28314758 | G10: =IFERROR(SUMIFS(Raw_Data!$D$5:$D$88,Raw_Data!$A$5:$A$88,$A10,Raw_Data!$B$5:$B$88,$B10,Raw_Data!$C$5:$C$88,"Total Borrowings (Debt Securities + Borrowings + Subordinated Liabilities)")/SUMIFS(Raw_Data!$D$5:$D$88,Raw_Data!$A$5:$A$88,$A10,Raw_Data!$B$5:$B$88,$B10,Raw_Data!$C$5:$C$88,"Total Equity"),"") -> 2.1708613 | H10: =IFERROR(SUMIFS(Raw_Data!$D$5:$D$88,Raw_Data!$A$5:$A$88,$A10,Raw_Data!$B$5:$B$88,$B10,Raw_Data!$C$5:$C$88,"CRAR (%)")/100,"") -> 0 | I10: =IFERROR(SUMIFS(Raw_Data!$D$5:$D$88,Raw_Data!$A$5:$A$88,$A10,Raw_Data!$B$5:$B$88,$B10,Raw_Data!$C$5:$C$88,"Gross NPA (Stage 3 Gross Carrying Amount)")/SUMIFS(Raw_Data!$D$5:$D$88,Raw_Data!$A$5:$A$88,$A10,Raw_Data!$B$5:$B$88,$B10,Raw_Data!$C$5:$C$88,"Total Gross Loans (for GNPA%)"),"") -> 0.01919372 | J10: =IFERROR(SUMIFS(Raw_Data!$D$5:$D$88,Raw_Data!$A$5:$A$88,$A10,Raw_Data!$B$5:$B$88,$B10,Raw_Data!$C$5:$C$88,"Net NPA (Stage 3 Net Carrying Amount)")/SUMIFS(Raw_Data!$D$5:$D$88,Raw_Data!$A$5:$A$88,$A10,Raw_Data!$B$5:$B$88,$B10,Raw_Data!$C$5:$C$88,"Total Net Loans (for NNPA%)"),"") -> 0.016964945

Sheet Notes_and_Assumptions
A1: Notes, Assumptions & Caveats
A3: 1. TATA CAPITAL — MERGER EFFECT (Important)
A4: Note 49 of the Tata Capital Annual Report 2024-25 states that FY25 figures include the effect of the
A5: merger of Tata Motors Finance Limited with the company. FY25 vs FY24 YoY comparisons are therefore
A6: NOT like-for-like / fully organic. Mention this caveat when presenting YoY growth figures.
A8: 2. CRAR figures are stored in Raw_Data as plain percentages (e.g. 16.91 = 16.91%) and converted to
A9: fractions in the Ratios sheet formula (divided by 100) so they display correctly as %.
A11: 3. GNPA / NNPA for Tata Capital use Ind AS 'Stage 3' classification as the equivalent of NPA,
A12: per RBI's prudential norms disclosure format used in the Annual Report.
A14: 4. Total Borrowings = Debt Securities + Borrowings (other than debt securities) + Subordinated Liabilities
A15: (excludes lease liabilities and other financial liabilities).
A17: 5. BAJAJ FINANCE & MANAPPURAM FINANCE — data rows are currently placeholders (highlighted yellow
... A26: https://www.tatacapital.com/content/dam/tata-capital/pdf/investors-and-financial-reports/annual-reports/24-25/tata-capital-limited.pdf
